caicurator/__init__.py
caicurator/cli.py
caicurator/constants.py
caicurator/core.py
caicurator/py.typed
caicurator/assets/template.pt
caicurator-0.7.0.dist-info/METADATA
caicurator-0.7.0.dist-info/WHEEL
caicurator-0.7.0.dist-info/entry_points.txt
caicurator-0.7.0.dist-info/licenses/LICENSE
caicurator-0.7.0.dist-info/RECORD
