Metadata-Version: 2.4
Name: caicurator
Version: 0.7.0
Summary: Curate and display Character AI web browser history
Project-URL: Homepage, https://github.com/eeriemyxi/caicurator
Project-URL: Documentation, https://github.com/eeriemyxi/caicurator#readme
Project-URL: Repository, https://github.com/eeriemyxi/caicurator
Project-URL: Bug Tracker, https://github.com/eeriemyxi/caicurator/issues
Author-email: eeriemyxi <myxi@duck.com>
License: Copyright (c) 2026 myxi@duck.com
License-File: LICENSE
Keywords: browser,cai,characterai,gui,history,python
Requires-Python: >=3.10
Requires-Dist: chameleon>=4.6.0
Requires-Dist: click>=8.3.1
Requires-Dist: curl-cffi>=0.14.0
Requires-Dist: loguru>=0.7.3
Requires-Dist: platformdirs>=4.5.1
